server.py
higress_ai_search_mcp_server-1.0.0.dist-info/METADATA
higress_ai_search_mcp_server-1.0.0.dist-info/WHEEL
higress_ai_search_mcp_server-1.0.0.dist-info/entry_points.txt
higress_ai_search_mcp_server-1.0.0.dist-info/top_level.txt
higress_ai_search_mcp_server-1.0.0.dist-info/RECORD
