Metadata-Version: 2.2
Name: higress-ai-search-mcp-server
Version: 1.0.0
Summary: Higress ai-search MCP Server
License:                                  Apache License
Requires-Python: >=3.10
Requires-Dist: fastmcp>=0.4.1
Requires-Dist: httpx>=0.24.0
Requires-Dist: tomli>=2.2.1
Requires-Dist: tomli-w>=1.2.0
